sopel_bugzilla/__init__.py
sopel_bugzilla/plugin.py
sopel_bugzilla-0.2.0.dist-info/licenses/COPYING
sopel_bugzilla-0.2.0.dist-info/METADATA
sopel_bugzilla-0.2.0.dist-info/WHEEL
sopel_bugzilla-0.2.0.dist-info/entry_points.txt
sopel_bugzilla-0.2.0.dist-info/top_level.txt
sopel_bugzilla-0.2.0.dist-info/RECORD
